devtools_meta_tags/__init__.py
devtools_meta_tags-1.0.1.dist-info/METADATA
devtools_meta_tags-1.0.1.dist-info/WHEEL
devtools_meta_tags-1.0.1.dist-info/top_level.txt
devtools_meta_tags-1.0.1.dist-info/RECORD
